big_phoney/__init__.py
big_phoney/big_phoney.py
big_phoney/phonetic_dictionary.py
big_phoney/prediction_model.py
big_phoney/prediction_model_utils.py
big_phoney/preprocessors.py
big_phoney/shared_constants.py
big_phoney/utils.py
big_phoney/data/bp-abbrev-dict.pkl
big_phoney/data/bp-phonetic-dict.pkl
big_phoney/data/bp-phonetic-symbols.pkl
big_phoney/data/bp-qty-abbrev-dict.pkl
big_phoney/data/prediction_model_weights.hdf5
big_phoney-1.0.1.dist-info/METADATA
big_phoney-1.0.1.dist-info/RECORD
big_phoney-1.0.1.dist-info/WHEEL
big_phoney-1.0.1.dist-info/top_level.txt
