Metadata-Version: 2.1
Name: big-phoney
Version: 1.0.1
Summary: Get phonetic spellings and syllable counts for any english word. Works with made up and non-dictionary words.
Home-page: https://github.com/repp/big-phoney
Author: Ryan Epp
Author-email: hey@ryanepp.com
License: UNKNOWN
Platform: UNKNOWN
Classifier: Programming Language :: Python :: 3
Classifier: License :: OSI Approved :: GNU General Public License v3 (GPLv3)
Classifier: Operating System :: OS Independent
Requires-Dist: numpy
Requires-Dist: keras
Requires-Dist: inflect
Requires-Dist: h5py
Requires-Dist: tensorflow
